[
  {
    "type": "paragraph_start"
  },
  {
    "type": "paragraph_text",
    "value": " "
  },
  {
    "type": "divine_name",
    "value": "YHWH"
  },
  {
    "type": "paragraph_text",
    "value": " said to Noah, “Come into the ark, you and all your household, for I consider you godly among this generation."
  },
  {
    "type": "paragraph_text",
    "value": "  "
  },
  {
    "type": "paragraph_text",
    "value": " You must take with you seven"
  },
  {
    "type": "paragraph_text",
    "value": " of every kind of clean animal,"
  },
  {
    "type": "paragraph_text",
    "value": " the male and its mate,"
  },
  {
    "type": "paragraph_text",
    "value": " two of every kind of unclean animal, the male and its mate, "
  },
  {
    "type": "paragraph_text",
    "value": " and also seven"
  },
  {
    "type": "paragraph_text",
    "value": " of every kind of bird in the sky, male and female,"
  },
  {
    "type": "paragraph_text",
    "value": " to preserve their offspring"
  },
  {
    "type": "paragraph_text",
    "value": " on the face of the earth. "
  },
  {
    "type": "paragraph_text",
    "value": " For in seven days"
  },
  {
    "type": "paragraph_text",
    "value": " I will cause it to rain"
  },
  {
    "type": "paragraph_text",
    "value": " on the earth for forty days and forty nights, and I will wipe from the face of the ground every living thing that I have made.”"
  },
  {
    "type": "paragraph_end"
  },
  {
    "type": "paragraph_start"
  },
  {
    "type": "paragraph_text",
    "value": " And Noah did all"
  },
  {
    "type": "paragraph_text",
    "value": " that "
  },
  {
    "type": "divine_name",
    "value": "YHWH"
  },
  {
    "type": "paragraph_text",
    "value": " commanded him."
  },
  {
    "type": "paragraph_end"
  },
  {
    "type": "paragraph_start"
  },
  {
    "type": "paragraph_text",
    "value": " Noah"
  },
  {
    "type": "paragraph_text",
    "value": " was 600 years old when the floodwaters engulfed"
  },
  {
    "type": "paragraph_text",
    "value": " the earth. "
  },
  {
    "type": "paragraph_text",
    "value": " Noah entered the ark along with his sons, his wife, and his sons’ wives because"
  },
  {
    "type": "paragraph_text",
    "value": " of the floodwaters. "
  },
  {
    "type": "paragraph_text",
    "value": " Pairs"
  },
  {
    "type": "paragraph_text",
    "value": " of clean animals, of unclean animals, of birds, and of everything that creeps along the ground, "
  },
  {
    "type": "paragraph_text",
    "value": " male and female, came into the ark to Noah,"
  },
  {
    "type": "paragraph_text",
    "value": " just as God had commanded him."
  },
  {
    "type": "paragraph_text",
    "value": "  "
  },
  {
    "type": "paragraph_text",
    "value": " And after seven days the floodwaters engulfed the earth."
  },
  {
    "type": "paragraph_end"
  },
  {
    "type": "paragraph_start"
  },
  {
    "type": "paragraph_text",
    "value": " In the six hundredth year of Noah’s life, in the second month, on the seventeenth day of the month – on that day all the fountains of the great deep"
  },
  {
    "type": "paragraph_text",
    "value": " burst open and the floodgates of the heavens"
  },
  {
    "type": "paragraph_text",
    "value": " were opened. "
  },
  {
    "type": "paragraph_text",
    "value": " And the rain fell"
  },
  {
    "type": "paragraph_text",
    "value": " on the earth forty days and forty nights."
  },
  {
    "type": "paragraph_end"
  },
  {
    "type": "paragraph_start"
  },
  {
    "type": "paragraph_text",
    "value": " On that very day Noah entered the ark, accompanied by his sons Shem, Ham, and Japheth, along with his wife and his sons’ three wives."
  },
  {
    "type": "paragraph_text",
    "value": "  "
  },
  {
    "type": "paragraph_text",
    "value": " They entered,"
  },
  {
    "type": "paragraph_text",
    "value": " along with every living creature after its kind, every animal after its kind, every creeping thing that creeps on the earth after its kind, and every bird after its kind, everything with wings."
  },
  {
    "type": "paragraph_text",
    "value": "  "
  },
  {
    "type": "paragraph_text",
    "value": " Pairs"
  },
  {
    "type": "paragraph_text",
    "value": " of all creatures"
  },
  {
    "type": "paragraph_text",
    "value": " that have the breath of life came into the ark to Noah. "
  },
  {
    "type": "paragraph_text",
    "value": " Those that entered were male and female,"
  },
  {
    "type": "paragraph_text",
    "value": " just as God commanded him. Then "
  },
  {
    "type": "divine_name",
    "value": "YHWH"
  },
  {
    "type": "paragraph_text",
    "value": " shut him in."
  },
  {
    "type": "paragraph_end"
  },
  {
    "type": "paragraph_start"
  },
  {
    "type": "paragraph_text",
    "value": " The flood engulfed the earth for forty days. As the waters increased, they lifted the ark and raised it above the earth. "
  },
  {
    "type": "paragraph_text",
    "value": " The waters completely overwhelmed"
  },
  {
    "type": "paragraph_text",
    "value": " the earth, and the ark floated"
  },
  {
    "type": "paragraph_text",
    "value": " on the surface of the waters. "
  },
  {
    "type": "paragraph_text",
    "value": " The waters completely inundated"
  },
  {
    "type": "paragraph_text",
    "value": " the earth so that even"
  },
  {
    "type": "paragraph_text",
    "value": " all the high mountains under the entire sky were covered. "
  },
  {
    "type": "paragraph_text",
    "value": " The waters rose more than twenty feet"
  },
  {
    "type": "paragraph_text",
    "value": " above the mountains."
  },
  {
    "type": "paragraph_text",
    "value": "  "
  },
  {
    "type": "paragraph_text",
    "value": " And all living things"
  },
  {
    "type": "paragraph_text",
    "value": " that moved on the earth died, including the birds, domestic animals, wild animals, all the creatures that swarm over the earth, and all humankind. "
  },
  {
    "type": "paragraph_text",
    "value": " Everything on dry land that had the breath of life"
  },
  {
    "type": "paragraph_text",
    "value": " in its nostrils died. "
  },
  {
    "type": "paragraph_text",
    "value": " So "
  },
  {
    "type": "divine_name",
    "value": "YHWH"
  },
  {
    "type": "paragraph_text",
    "value": " destroyed"
  },
  {
    "type": "paragraph_text",
    "value": " every living thing that was on the surface of the ground, including people, animals, creatures that creep along the ground, and birds of the sky."
  },
  {
    "type": "paragraph_text",
    "value": " They were wiped off the earth. Only Noah and those who were with him in the ark survived."
  },
  {
    "type": "paragraph_text",
    "value": "  "
  },
  {
    "type": "paragraph_text",
    "value": " The waters prevailed over"
  },
  {
    "type": "paragraph_text",
    "value": " the earth for 150 days."
  },
  {
    "type": "paragraph_end"
  }
]